PyUnTarZip/__init__.py
PyUnTarZip/__main__.py
PyUnTarZip-0.0.2.dist-info/LICENSE
PyUnTarZip-0.0.2.dist-info/METADATA
PyUnTarZip-0.0.2.dist-info/WHEEL
PyUnTarZip-0.0.2.dist-info/top_level.txt
PyUnTarZip-0.0.2.dist-info/RECORD
