Metadata-Version: 2.1
Name: PyUnTarZip
Version: 0.0.2
Summary: PyUnTarZip is a simple Python tool for compressing and decompressing files in ZIP and TAR formats.
Home-page: 
Author: Claudio Torres Arbe
Author-email: claudiotarbe@gmail.com
Classifier: Programming Language :: Python :: 3.8
Classifier: License :: OSI Approved :: MIT License
Classifier: Operating System :: OS Independent
Requires-Python: >=3.6
License-File: LICENSE
